odoo9_addon_sale_medical_prescription-9.0.2.0.0-py2.7-nspkg.pth
odoo_addons/sale_medical_prescription/__openerp__.py
odoo_addons/sale_medical_prescription/__init__.py
odoo_addons/sale_medical_prescription/README.rst
odoo_addons/sale_medical_prescription/models/medical_medicament.py
odoo_addons/sale_medical_prescription/models/medical_prescription_order.py
odoo_addons/sale_medical_prescription/models/medical_patient.py
odoo_addons/sale_medical_prescription/models/sale_order_line.py
odoo_addons/sale_medical_prescription/models/medical_prescription_order_line.py
odoo_addons/sale_medical_prescription/models/sale_order.py
odoo_addons/sale_medical_prescription/models/__init__.py
odoo_addons/sale_medical_prescription/models/medical_physician.py
odoo_addons/sale_medical_prescription/models/medical_pharmacy.py
odoo_addons/sale_medical_prescription/models/product_category.py
odoo_addons/sale_medical_prescription/i18n/es_CO.po
odoo_addons/sale_medical_prescription/i18n/pt_BR.po
odoo_addons/sale_medical_prescription/views/prescription_order_view.xml
odoo_addons/sale_medical_prescription/views/medical_patient_view.xml
odoo_addons/sale_medical_prescription/views/sale_order_view.xml
odoo_addons/sale_medical_prescription/views/medical_physician_view.xml
odoo_addons/sale_medical_prescription/views/medical_pharmacy_view.xml
odoo_addons/sale_medical_prescription/views/prescription_order_line_view.xml
odoo_addons/sale_medical_prescription/views/medical_medicament_view.xml
odoo_addons/sale_medical_prescription/wizards/medical_sale_line_temp.py
odoo_addons/sale_medical_prescription/wizards/medical_sale_wizard.py
odoo_addons/sale_medical_prescription/wizards/medical_sale_temp_view.xml
odoo_addons/sale_medical_prescription/wizards/medical_sale_temp.py
odoo_addons/sale_medical_prescription/wizards/medical_sale_wizard_view.xml
odoo_addons/sale_medical_prescription/wizards/__init__.py
odoo_addons/sale_medical_prescription/data/product_category_data.xml
odoo9_addon_sale_medical_prescription-9.0.2.0.0.dist-info/top_level.txt
odoo9_addon_sale_medical_prescription-9.0.2.0.0.dist-info/WHEEL
odoo9_addon_sale_medical_prescription-9.0.2.0.0.dist-info/RECORD
odoo9_addon_sale_medical_prescription-9.0.2.0.0.dist-info/metadata.json
odoo9_addon_sale_medical_prescription-9.0.2.0.0.dist-info/DESCRIPTION.rst
odoo9_addon_sale_medical_prescription-9.0.2.0.0.dist-info/METADATA
odoo9_addon_sale_medical_prescription-9.0.2.0.0.dist-info/namespace_packages.txt
